django_privacy_mgmt/__init__.py
django_privacy_mgmt/admin.py
django_privacy_mgmt/models.py
django_privacy_mgmt/boilerplates/bootstrap3/templates/django_privacy_mgmt/base.html
django_privacy_mgmt/locale/de/LC_MESSAGES/django.mo
django_privacy_mgmt/locale/de/LC_MESSAGES/django.po
django_privacy_mgmt/locale/en/LC_MESSAGES/django.po
django_privacy_mgmt/locale/fr/LC_MESSAGES/django.mo
django_privacy_mgmt/locale/fr/LC_MESSAGES/django.po
django_privacy_mgmt/locale/it/LC_MESSAGES/django.mo
django_privacy_mgmt/locale/it/LC_MESSAGES/django.po
django_privacy_mgmt/migrations/0001_initial.py
django_privacy_mgmt/migrations/0002_auto_20190902_1118.py
django_privacy_mgmt/migrations/0003_auto_20200729_0338.py
django_privacy_mgmt/migrations/__init__.py
django_privacy_mgmt/static/css/libs/jquery.fancybox.css
django_privacy_mgmt/static/django_privacy_mgmt/css/main.css
django_privacy_mgmt/static/django_privacy_mgmt/js/main.js
django_privacy_mgmt/static/django_privacy_mgmt/js/libs/jquery.cookie.2.2.0.js
django_privacy_mgmt/static/js/django_privacy_mgmt/main.js
django_privacy_mgmt/static/js/libs/jquery.cookie.2.2.0.js
django_privacy_mgmt/static/js/libs/jquery.fancybox.js
django_privacy_mgmt/static/js/libs/jquery.min.js
django_privacy_mgmt/templates/django_privacy_mgmt/api.html
django_privacy_mgmt/templates/django_privacy_mgmt/banner.html
django_privacy_mgmt/templates/django_privacy_mgmt/link.html
django_privacy_mgmt/templates/django_privacy_mgmt/popup.html
django_privacy_mgmt/templatetags/__init__.py
django_privacy_mgmt/templatetags/privacy.py
django_privacy_mgmt-0.0.21.dist-info/LICENSE
django_privacy_mgmt-0.0.21.dist-info/METADATA
django_privacy_mgmt-0.0.21.dist-info/WHEEL
django_privacy_mgmt-0.0.21.dist-info/top_level.txt
django_privacy_mgmt-0.0.21.dist-info/RECORD
