Metadata-Version: 2.1
Name: django-privacy-mgmt
Version: 0.0.21
Summary: This package provides a simple interface to provide GDPR-compliant cookie and tracking management on a website.
Home-page: https://gitlab.com/what-digital/django-privacy-mgmt/tree/master
Author: what.digital
Author-email: mario@what.digital
License: UNKNOWN
Download-URL: https://gitlab.com/what-digital/django-privacy-mgmt/-/archive/0.0.21/django-privacy-mgmt-0.0.21.tar.gz
Platform: OS Independent
Requires-Dist: django-parler (>=1.8.1)
Requires-Dist: Django (>=1.8)
Requires-Dist: django-sekizai (>=0.10.0)
